flywheel_common/__init__.py
flywheel_common/errors.py
flywheel_common/logging/__init__.py
flywheel_common/logging/context_logger.py
flywheel_common/logging/extra_formatter.py
flywheel_common/logging/json_formatter.py
flywheel_common/logging/setup.py
flywheel_common/providers/__init__.py
flywheel_common/providers/creds.py
flywheel_common/providers/provider.py
flywheel_common/providers/compute/__init__.py
flywheel_common/providers/compute/base.py
flywheel_common/providers/storage/__init__.py
flywheel_common/providers/storage/base.py
flywheel_common/storage/__init__.py
flywheel_common/storage/interface.py
flywheel_common/storage/util.py
tests/__init__.py
tests/test_errors.py
tests/test_extras_wrapper.py
tests/test_formatter.py
tests/test_providers.py
tests/test_storage.py
flywheel_common-17.8.2.dist-info/METADATA
flywheel_common-17.8.2.dist-info/WHEEL
flywheel_common-17.8.2.dist-info/top_level.txt
flywheel_common-17.8.2.dist-info/RECORD
