Metadata-Version: 2.1
Name: flywheel-common
Version: 17.8.2
Summary: Collection of toolkits to be used across the Flywheel platform
Home-page: https://github.com/flywheel-io/flywheel-common
Author: Flywheel
Author-email: support@flywheel.io
License: MIT
Platform: UNKNOWN
Requires-Dist: pyyaml <7.0,>=5.3.1
Requires-Dist: enum34 ==1.1.6 ; python_version < "3.4"
Requires-Dist: marshmallow <4.0,>=3.19.0 ; python_version >= "3.7" and python_version < "4.0"
Provides-Extra: gevent
Requires-Dist: gevent-inotifyx ==0.2 ; extra == 'gevent'
